Metadata-Version: 2.1
Name: hello_world-regal
Version: 0.0.1
Summary: A hello-world example package
Home-page: https://www.linkedin.com/in/adewaleadeboye/
Author: Adewale
Author-email: adewaleadeboye10@gmail.com
Classifier: Programming Language :: Python :: 3
Classifier: License :: OSI Approved :: MIT License
Classifier: Operating System :: OS Independent
